{"ID":"20220410","Date":"2022-04-10T00:00:52.0097757+03:00","DayNo":"","Currencies":[{"Code":"","CrossOrder":0,"Unit":0,"CurrencyNameTR":"ABD DOLARI","CurrencyName":"US DOLLAR","ForexBuying":14.7213,"BanknotBuying":0,"BanknoteSelling":14.7699,"ForexSelling":14.7478,"CrossRateUSD":0,"CrossRateOther":0},{"Code":"","CrossOrder":1,"Unit":0,"CurrencyNameTR":"AVUSTRALYA DOLARI","CurrencyName":"AUSTRALIAN DOLLAR","ForexBuying":10.9638,"BanknotBuying":0,"BanknoteSelling":11.1015,"ForexSelling":11.0353,"CrossRateUSD":1.3396,"CrossRateOther":0},{"Code":"","CrossOrder":2,"Unit":0,"CurrencyNameTR":"DANİMARKA KRONU","CurrencyName":"DANISH KRONE","ForexBuying":2.1481,"BanknotBuying":0,"BanknoteSelling":2.1636,"ForexSelling":2.1586,"CrossRateUSD":6.8425,"CrossRateOther":0},{"Code":"","CrossOrder":9,"Unit":0,"CurrencyNameTR":"EURO","CurrencyName":"EURO","ForexBuying":16.0012,"BanknotBuying":0,"BanknoteSelling":16.0541,"ForexSelling":16.03,"CrossRateUSD":0,"CrossRateOther":1.0869},{"Code":"","CrossOrder":10,"Unit":0,"CurrencyNameTR":"İNGİLİZ STERLİNİ","CurrencyName":"POUND STERLING","ForexBuying":19.1645,"BanknotBuying":0,"BanknoteSelling":19.2933,"ForexSelling":19.2644,"CrossRateUSD":0,"CrossRateOther":1.304},{"Code":"","CrossOrder":3,"Unit":0,"CurrencyNameTR":"İSVİÇRE FRANGI","CurrencyName":"SWISS FRANK","ForexBuying":15.7099,"BanknotBuying":0,"BanknoteSelling":15.8344,"ForexSelling":15.8107,"CrossRateUSD":0.9349,"CrossRateOther":0},{"Code":"","CrossOrder":4,"Unit":0,"CurrencyNameTR":"İSVEÇ KRONU","CurrencyName":"SWEDISH KRONA","ForexBuying":1.5496,"BanknotBuying":0,"BanknoteSelling":1.5692,"ForexSelling":1.5656,"CrossRateUSD":9.4598,"CrossRateOther":0},{"Code":"","CrossOrder":6,"Unit":0,"CurrencyNameTR":"KANADA DOLARI","CurrencyName":"CANADIAN DOLLAR","ForexBuying":11.6779,"BanknotBuying":0,"BanknoteSelling":11.7751,"ForexSelling":11.7306,"CrossRateUSD":1.2589,"CrossRateOther":0},{"Code":"","CrossOrder":11,"Unit":0,"CurrencyNameTR":"KUVEYT DİNARI","CurrencyName":"KUWAITI DINAR","ForexBuying":48.0104,"BanknotBuying":0,"BanknoteSelling":49.3682,"ForexSelling":48.6386,"CrossRateUSD":0,"CrossRateOther":3.2797},{"Code":"","CrossOrder":7,"Unit":0,"CurrencyNameTR":"NORVEÇ KRONU","CurrencyName":"NORWEGIAN KRONE","ForexBuying":1.6729,"BanknotBuying":0,"BanknoteSelling":1.688,"ForexSelling":1.6841,"CrossRateUSD":8.7783,"CrossRateOther":0},{"Code":"","CrossOrder":8,"Unit":0,"CurrencyNameTR":"SUUDİ ARABİSTAN RİYALİ","CurrencyName":"SAUDI RIYAL","ForexBuying":3.9254,"BanknotBuying":0,"BanknoteSelling":3.9619,"ForexSelling":3.9324,"CrossRateUSD":3.7503,"CrossRateOther":0},{"Code":"","CrossOrder":5,"Unit":0,"CurrencyNameTR":"JAPON YENİ","CurrencyName":"JAPENESE YEN","ForexBuying":11.8342,"BanknotBuying":0,"BanknoteSelling":11.9578,"ForexSelling":11.9125,"CrossRateUSD":124.1,"CrossRateOther":0},{"Code":"","CrossOrder":12,"Unit":0,"CurrencyNameTR":"BULGAR LEVASI","CurrencyName":"BULGARIAN LEV","ForexBuying":8.1354,"BanknotBuying":0,"BanknoteSelling":0,"ForexSelling":8.2418,"CrossRateUSD":1.7994,"CrossRateOther":0},{"Code":"","CrossOrder":13,"Unit":0,"CurrencyNameTR":"RUMEN LEYİ","CurrencyName":"NEW LEU","ForexBuying":3.219,"BanknotBuying":0,"BanknoteSelling":0,"ForexSelling":3.2612,"CrossRateUSD":4.5476,"CrossRateOther":0},{"Code":"","CrossOrder":14,"Unit":0,"CurrencyNameTR":"RUS RUBLESİ","CurrencyName":"RUSSIAN ROUBLE","ForexBuying":0.18615,"BanknotBuying":0,"BanknoteSelling":0,"ForexSelling":0.18859,"CrossRateUSD":78.64,"CrossRateOther":0},{"Code":"","CrossOrder":15,"Unit":0,"CurrencyNameTR":"İRAN RİYALİ","CurrencyName":"IRANIAN RIAL","ForexBuying":0.03485,"BanknotBuying":0,"BanknoteSelling":0,"ForexSelling":0.03531,"CrossRateUSD":42000,"CrossRateOther":0},{"Code":"","CrossOrder":16,"Unit":0,"CurrencyNameTR":"ÇİN YUANI","CurrencyName":"CHINESE RENMINBI","ForexBuying":2.3005,"BanknotBuying":0,"BanknoteSelling":0,"ForexSelling":2.3306,"CrossRateUSD":6.3634,"CrossRateOther":0},{"Code":"","CrossOrder":17,"Unit":0,"CurrencyNameTR":"PAKİSTAN RUPİSİ","CurrencyName":"PAKISTANI RUPEE","ForexBuying":0.0782,"BanknotBuying":0,"BanknoteSelling":0,"ForexSelling":0.07923,"CrossRateUSD":187.19,"CrossRateOther":0},{"Code":"","CrossOrder":18,"Unit":0,"CurrencyNameTR":"KATAR RİYALİ","CurrencyName":"QATARI RIAL","ForexBuying":4.0126,"BanknotBuying":0,"BanknoteSelling":0,"ForexSelling":4.0651,"CrossRateUSD":3.6482,"CrossRateOther":0},{"Code":"","CrossOrder":19,"Unit":0,"CurrencyNameTR":"GÜNEY KORE WONU","CurrencyName":"SOUTH KOREAN WON","ForexBuying":0.01194,"BanknotBuying":0,"BanknoteSelling":0,"ForexSelling":0.01209,"CrossRateUSD":1226,"CrossRateOther":0},{"Code":"","CrossOrder":20,"Unit":0,"CurrencyNameTR":"AZERBAYCAN YENİ MANATI","CurrencyName":"AZERBAIJANI NEW MANAT","ForexBuying":8.6161,"BanknotBuying":0,"BanknoteSelling":0,"ForexSelling":8.7289,"CrossRateUSD":1.699,"CrossRateOther":0},{"Code":"","CrossOrder":21,"Unit":0,"CurrencyNameTR":"BİRLEŞİK ARAP EMİRLİKLERİ DİRHEMİ","CurrencyName":"UNITED ARAB EMIRATES DIRHAM","ForexBuying":3.9855,"BanknotBuying":0,"BanknoteSelling":0,"ForexSelling":4.0376,"CrossRateUSD":3.6731,"CrossRateOther":0},{"Code":"","CrossOrder":0,"Unit":0,"CurrencyNameTR":"ÖZEL ÇEKME HAKKI (SDR)                            ","CurrencyName":"SPECIAL DRAWING RIGHT (SDR)                       ","ForexBuying":20.1967,"BanknotBuying":0,"BanknoteSelling":0,"ForexSelling":0,"CrossRateUSD":0,"CrossRateOther":1.3707}]}
{"ID":"20220410","Date":"2022-04-10T00:01:08.711287+03:00","DayNo":"","Currencies":[{"Code":"","CrossOrder":0,"Unit":0,"CurrencyNameTR":"ABD DOLARI","CurrencyName":"US DOLLAR","ForexBuying":14.7213,"BanknotBuying":0,"BanknoteSelling":14.7699,"ForexSelling":14.7478,"CrossRateUSD":0,"CrossRateOther":0},{"Code":"","CrossOrder":1,"Unit":0,"CurrencyNameTR":"AVUSTRALYA DOLARI","CurrencyName":"AUSTRALIAN DOLLAR","ForexBuying":10.9638,"BanknotBuying":0,"BanknoteSelling":11.1015,"ForexSelling":11.0353,"CrossRateUSD":1.3396,"CrossRateOther":0},{"Code":"","CrossOrder":2,"Unit":0,"CurrencyNameTR":"DANİMARKA KRONU","CurrencyName":"DANISH KRONE","ForexBuying":2.1481,"BanknotBuying":0,"BanknoteSelling":2.1636,"ForexSelling":2.1586,"CrossRateUSD":6.8425,"CrossRateOther":0},{"Code":"","CrossOrder":9,"Unit":0,"CurrencyNameTR":"EURO","CurrencyName":"EURO","ForexBuying":16.0012,"BanknotBuying":0,"BanknoteSelling":16.0541,"ForexSelling":16.03,"CrossRateUSD":0,"CrossRateOther":1.0869},{"Code":"","CrossOrder":10,"Unit":0,"CurrencyNameTR":"İNGİLİZ STERLİNİ","CurrencyName":"POUND STERLING","ForexBuying":19.1645,"BanknotBuying":0,"BanknoteSelling":19.2933,"ForexSelling":19.2644,"CrossRateUSD":0,"CrossRateOther":1.304},{"Code":"","CrossOrder":3,"Unit":0,"CurrencyNameTR":"İSVİÇRE FRANGI","CurrencyName":"SWISS FRANK","ForexBuying":15.7099,"BanknotBuying":0,"BanknoteSelling":15.8344,"ForexSelling":15.8107,"CrossRateUSD":0.9349,"CrossRateOther":0},{"Code":"","CrossOrder":4,"Unit":0,"CurrencyNameTR":"İSVEÇ KRONU","CurrencyName":"SWEDISH KRONA","ForexBuying":1.5496,"BanknotBuying":0,"BanknoteSelling":1.5692,"ForexSelling":1.5656,"CrossRateUSD":9.4598,"CrossRateOther":0},{"Code":"","CrossOrder":6,"Unit":0,"CurrencyNameTR":"KANADA DOLARI","CurrencyName":"CANADIAN DOLLAR","ForexBuying":11.6779,"BanknotBuying":0,"BanknoteSelling":11.7751,"ForexSelling":11.7306,"CrossRateUSD":1.2589,"CrossRateOther":0},{"Code":"","CrossOrder":11,"Unit":0,"CurrencyNameTR":"KUVEYT DİNARI","CurrencyName":"KUWAITI DINAR","ForexBuying":48.0104,"BanknotBuying":0,"BanknoteSelling":49.3682,"ForexSelling":48.6386,"CrossRateUSD":0,"CrossRateOther":3.2797},{"Code":"","CrossOrder":7,"Unit":0,"CurrencyNameTR":"NORVEÇ KRONU","CurrencyName":"NORWEGIAN KRONE","ForexBuying":1.6729,"BanknotBuying":0,"BanknoteSelling":1.688,"ForexSelling":1.6841,"CrossRateUSD":8.7783,"CrossRateOther":0},{"Code":"","CrossOrder":8,"Unit":0,"CurrencyNameTR":"SUUDİ ARABİSTAN RİYALİ","CurrencyName":"SAUDI RIYAL","ForexBuying":3.9254,"BanknotBuying":0,"BanknoteSelling":3.9619,"ForexSelling":3.9324,"CrossRateUSD":3.7503,"CrossRateOther":0},{"Code":"","CrossOrder":5,"Unit":0,"CurrencyNameTR":"JAPON YENİ","CurrencyName":"JAPENESE YEN","ForexBuying":11.8342,"BanknotBuying":0,"BanknoteSelling":11.9578,"ForexSelling":11.9125,"CrossRateUSD":124.1,"CrossRateOther":0},{"Code":"","CrossOrder":12,"Unit":0,"CurrencyNameTR":"BULGAR LEVASI","CurrencyName":"BULGARIAN LEV","ForexBuying":8.1354,"BanknotBuying":0,"BanknoteSelling":0,"ForexSelling":8.2418,"CrossRateUSD":1.7994,"CrossRateOther":0},{"Code":"","CrossOrder":13,"Unit":0,"CurrencyNameTR":"RUMEN LEYİ","CurrencyName":"NEW LEU","ForexBuying":3.219,"BanknotBuying":0,"BanknoteSelling":0,"ForexSelling":3.2612,"CrossRateUSD":4.5476,"CrossRateOther":0},{"Code":"","CrossOrder":14,"Unit":0,"CurrencyNameTR":"RUS RUBLESİ","CurrencyName":"RUSSIAN ROUBLE","ForexBuying":0.18615,"BanknotBuying":0,"BanknoteSelling":0,"ForexSelling":0.18859,"CrossRateUSD":78.64,"CrossRateOther":0},{"Code":"","CrossOrder":15,"Unit":0,"CurrencyNameTR":"İRAN RİYALİ","CurrencyName":"IRANIAN RIAL","ForexBuying":0.03485,"BanknotBuying":0,"BanknoteSelling":0,"ForexSelling":0.03531,"CrossRateUSD":42000,"CrossRateOther":0},{"Code":"","CrossOrder":16,"Unit":0,"CurrencyNameTR":"ÇİN YUANI","CurrencyName":"CHINESE RENMINBI","ForexBuying":2.3005,"BanknotBuying":0,"BanknoteSelling":0,"ForexSelling":2.3306,"CrossRateUSD":6.3634,"CrossRateOther":0},{"Code":"","CrossOrder":17,"Unit":0,"CurrencyNameTR":"PAKİSTAN RUPİSİ","CurrencyName":"PAKISTANI RUPEE","ForexBuying":0.0782,"BanknotBuying":0,"BanknoteSelling":0,"ForexSelling":0.07923,"CrossRateUSD":187.19,"CrossRateOther":0},{"Code":"","CrossOrder":18,"Unit":0,"CurrencyNameTR":"KATAR RİYALİ","CurrencyName":"QATARI RIAL","ForexBuying":4.0126,"BanknotBuying":0,"BanknoteSelling":0,"ForexSelling":4.0651,"CrossRateUSD":3.6482,"CrossRateOther":0},{"Code":"","CrossOrder":19,"Unit":0,"CurrencyNameTR":"GÜNEY KORE WONU","CurrencyName":"SOUTH KOREAN WON","ForexBuying":0.01194,"BanknotBuying":0,"BanknoteSelling":0,"ForexSelling":0.01209,"CrossRateUSD":1226,"CrossRateOther":0},{"Code":"","CrossOrder":20,"Unit":0,"CurrencyNameTR":"AZERBAYCAN YENİ MANATI","CurrencyName":"AZERBAIJANI NEW MANAT","ForexBuying":8.6161,"BanknotBuying":0,"BanknoteSelling":0,"ForexSelling":8.7289,"CrossRateUSD":1.699,"CrossRateOther":0},{"Code":"","CrossOrder":21,"Unit":0,"CurrencyNameTR":"BİRLEŞİK ARAP EMİRLİKLERİ DİRHEMİ","CurrencyName":"UNITED ARAB EMIRATES DIRHAM","ForexBuying":3.9855,"BanknotBuying":0,"BanknoteSelling":0,"ForexSelling":4.0376,"CrossRateUSD":3.6731,"CrossRateOther":0},{"Code":"","CrossOrder":0,"Unit":0,"CurrencyNameTR":"ÖZEL ÇEKME HAKKI (SDR)                            ","CurrencyName":"SPECIAL DRAWING RIGHT (SDR)                       ","ForexBuying":20.1967,"BanknotBuying":0,"BanknoteSelling":0,"ForexSelling":0,"CrossRateUSD":0,"CrossRateOther":1.3707}]}
{"ID":"20220410","Date":"2022-04-10T00:01:15.4621697+03:00","DayNo":"","Currencies":[{"Code":"","CrossOrder":0,"Unit":0,"CurrencyNameTR":"ABD DOLARI","CurrencyName":"US DOLLAR","ForexBuying":14.7213,"BanknotBuying":0,"BanknoteSelling":14.7699,"ForexSelling":14.7478,"CrossRateUSD":0,"CrossRateOther":0},{"Code":"","CrossOrder":1,"Unit":0,"CurrencyNameTR":"AVUSTRALYA DOLARI","CurrencyName":"AUSTRALIAN DOLLAR","ForexBuying":10.9638,"BanknotBuying":0,"BanknoteSelling":11.1015,"ForexSelling":11.0353,"CrossRateUSD":1.3396,"CrossRateOther":0},{"Code":"","CrossOrder":2,"Unit":0,"CurrencyNameTR":"DANİMARKA KRONU","CurrencyName":"DANISH KRONE","ForexBuying":2.1481,"BanknotBuying":0,"BanknoteSelling":2.1636,"ForexSelling":2.1586,"CrossRateUSD":6.8425,"CrossRateOther":0},{"Code":"","CrossOrder":9,"Unit":0,"CurrencyNameTR":"EURO","CurrencyName":"EURO","ForexBuying":16.0012,"BanknotBuying":0,"BanknoteSelling":16.0541,"ForexSelling":16.03,"CrossRateUSD":0,"CrossRateOther":1.0869},{"Code":"","CrossOrder":10,"Unit":0,"CurrencyNameTR":"İNGİLİZ STERLİNİ","CurrencyName":"POUND STERLING","ForexBuying":19.1645,"BanknotBuying":0,"BanknoteSelling":19.2933,"ForexSelling":19.2644,"CrossRateUSD":0,"CrossRateOther":1.304},{"Code":"","CrossOrder":3,"Unit":0,"CurrencyNameTR":"İSVİÇRE FRANGI","CurrencyName":"SWISS FRANK","ForexBuying":15.7099,"BanknotBuying":0,"BanknoteSelling":15.8344,"ForexSelling":15.8107,"CrossRateUSD":0.9349,"CrossRateOther":0},{"Code":"","CrossOrder":4,"Unit":0,"CurrencyNameTR":"İSVEÇ KRONU","CurrencyName":"SWEDISH KRONA","ForexBuying":1.5496,"BanknotBuying":0,"BanknoteSelling":1.5692,"ForexSelling":1.5656,"CrossRateUSD":9.4598,"CrossRateOther":0},{"Code":"","CrossOrder":6,"Unit":0,"CurrencyNameTR":"KANADA DOLARI","CurrencyName":"CANADIAN DOLLAR","ForexBuying":11.6779,"BanknotBuying":0,"BanknoteSelling":11.7751,"ForexSelling":11.7306,"CrossRateUSD":1.2589,"CrossRateOther":0},{"Code":"","CrossOrder":11,"Unit":0,"CurrencyNameTR":"KUVEYT DİNARI","CurrencyName":"KUWAITI DINAR","ForexBuying":48.0104,"BanknotBuying":0,"BanknoteSelling":49.3682,"ForexSelling":48.6386,"CrossRateUSD":0,"CrossRateOther":3.2797},{"Code":"","CrossOrder":7,"Unit":0,"CurrencyNameTR":"NORVEÇ KRONU","CurrencyName":"NORWEGIAN KRONE","ForexBuying":1.6729,"BanknotBuying":0,"BanknoteSelling":1.688,"ForexSelling":1.6841,"CrossRateUSD":8.7783,"CrossRateOther":0},{"Code":"","CrossOrder":8,"Unit":0,"CurrencyNameTR":"SUUDİ ARABİSTAN RİYALİ","CurrencyName":"SAUDI RIYAL","ForexBuying":3.9254,"BanknotBuying":0,"BanknoteSelling":3.9619,"ForexSelling":3.9324,"CrossRateUSD":3.7503,"CrossRateOther":0},{"Code":"","CrossOrder":5,"Unit":0,"CurrencyNameTR":"JAPON YENİ","CurrencyName":"JAPENESE YEN","ForexBuying":11.8342,"BanknotBuying":0,"BanknoteSelling":11.9578,"ForexSelling":11.9125,"CrossRateUSD":124.1,"CrossRateOther":0},{"Code":"","CrossOrder":12,"Unit":0,"CurrencyNameTR":"BULGAR LEVASI","CurrencyName":"BULGARIAN LEV","ForexBuying":8.1354,"BanknotBuying":0,"BanknoteSelling":0,"ForexSelling":8.2418,"CrossRateUSD":1.7994,"CrossRateOther":0},{"Code":"","CrossOrder":13,"Unit":0,"CurrencyNameTR":"RUMEN LEYİ","CurrencyName":"NEW LEU","ForexBuying":3.219,"BanknotBuying":0,"BanknoteSelling":0,"ForexSelling":3.2612,"CrossRateUSD":4.5476,"CrossRateOther":0},{"Code":"","CrossOrder":14,"Unit":0,"CurrencyNameTR":"RUS RUBLESİ","CurrencyName":"RUSSIAN ROUBLE","ForexBuying":0.18615,"BanknotBuying":0,"BanknoteSelling":0,"ForexSelling":0.18859,"CrossRateUSD":78.64,"CrossRateOther":0},{"Code":"","CrossOrder":15,"Unit":0,"CurrencyNameTR":"İRAN RİYALİ","CurrencyName":"IRANIAN RIAL","ForexBuying":0.03485,"BanknotBuying":0,"BanknoteSelling":0,"ForexSelling":0.03531,"CrossRateUSD":42000,"CrossRateOther":0},{"Code":"","CrossOrder":16,"Unit":0,"CurrencyNameTR":"ÇİN YUANI","CurrencyName":"CHINESE RENMINBI","ForexBuying":2.3005,"BanknotBuying":0,"BanknoteSelling":0,"ForexSelling":2.3306,"CrossRateUSD":6.3634,"CrossRateOther":0},{"Code":"","CrossOrder":17,"Unit":0,"CurrencyNameTR":"PAKİSTAN RUPİSİ","CurrencyName":"PAKISTANI RUPEE","ForexBuying":0.0782,"BanknotBuying":0,"BanknoteSelling":0,"ForexSelling":0.07923,"CrossRateUSD":187.19,"CrossRateOther":0},{"Code":"","CrossOrder":18,"Unit":0,"CurrencyNameTR":"KATAR RİYALİ","CurrencyName":"QATARI RIAL","ForexBuying":4.0126,"BanknotBuying":0,"BanknoteSelling":0,"ForexSelling":4.0651,"CrossRateUSD":3.6482,"CrossRateOther":0},{"Code":"","CrossOrder":19,"Unit":0,"CurrencyNameTR":"GÜNEY KORE WONU","CurrencyName":"SOUTH KOREAN WON","ForexBuying":0.01194,"BanknotBuying":0,"BanknoteSelling":0,"ForexSelling":0.01209,"CrossRateUSD":1226,"CrossRateOther":0},{"Code":"","CrossOrder":20,"Unit":0,"CurrencyNameTR":"AZERBAYCAN YENİ MANATI","CurrencyName":"AZERBAIJANI NEW MANAT","ForexBuying":8.6161,"BanknotBuying":0,"BanknoteSelling":0,"ForexSelling":8.7289,"CrossRateUSD":1.699,"CrossRateOther":0},{"Code":"","CrossOrder":21,"Unit":0,"CurrencyNameTR":"BİRLEŞİK ARAP EMİRLİKLERİ DİRHEMİ","CurrencyName":"UNITED ARAB EMIRATES DIRHAM","ForexBuying":3.9855,"BanknotBuying":0,"BanknoteSelling":0,"ForexSelling":4.0376,"CrossRateUSD":3.6731,"CrossRateOther":0},{"Code":"","CrossOrder":0,"Unit":0,"CurrencyNameTR":"ÖZEL ÇEKME HAKKI (SDR)                            ","CurrencyName":"SPECIAL DRAWING RIGHT (SDR)                       ","ForexBuying":20.1967,"BanknotBuying":0,"BanknoteSelling":0,"ForexSelling":0,"CrossRateUSD":0,"CrossRateOther":1.3707}]}
